{
  "playtime": 10667.86,
  "modes": {
    "watch": {
      "playtime": 9057.5,
      "clear": 16,
      "clearcount": {
        "undyne": 1,
        "ichigotybw": 1,
        "uchiha obito": 2,
        "arimak": 1,
        "yuta (dr animation)": 1,
        "bakugok": 1,
        "itadori modulo openggl": 1,
        "accelerator jvl all forms": 4,
        "ulquiorra": 1,
        "grimmjow": 1,
        "mahoraga": 1,
        "madara uchiha": 1
      }
    },
    "arcade": {
      "playtime": 1610.36,
      "clear": 1,
      "ranking": [
        {
          "score": 376700,
          "time": 1413.88,
          "win": 11,
          "lose": 0,
          "consecutive": 1,
          "name": "",
          "chars": [
            "obito"
          ],
          "tmode": 0,
          "ailevel": 8
        },
        {
          "score": 105900,
          "time": 196.48,
          "win": 0,
          "lose": 1,
          "consecutive": 0,
          "name": "AAA",
          "chars": [
            "gokussg"
          ],
          "tmode": 0,
          "ailevel": 8
        }
      ],
      "clearcount": {
        "obito": 1
      }
    },
    "training": {
      "playtime": 0,
      "clear": 0
    }
  }
}